Square_wave_assignment/square_wave_gen.v
module square_wave_gen (
    input clk,          
    input reset,        
    output reg out1,    
    output reg out2    
);

    reg [1:0] counter;  

    always @(posedge clk or posedge reset) begin
        if (reset) begin
            counter <= 0;
        end 
        else begin
            counter <= counter + 1; 
        end
    end

    always @(*) begin
        if (reset) begin
            out1 = 0;
            out2 = 0;
        end 
        else begin
            out1 = (counter == 0 || counter == 1); // High for counter = 0,1
            out2 = (counter == 1 || counter == 2); // High for counter = 1,2
        end
    end

endmodule

Square_wave_assignment/tb_square_wave_gen.v

module tb_square_wave_gen;
    reg clk;            
    reg reset;          
    wire out1; 
    wire out2;        

    square_wave_gen uut (
        .clk(clk),
        .reset(reset),
        .out1(out1),
        .out2(out2)
    );

    initial begin
        $dumpfile("square_wave.vcd"); 
        $dumpvars(0, tb_square_wave_gen); 
    end

    initial begin
        clk = 0;
        forever #125 clk = ~clk;  //4 Mhz clock
    end

    initial begin
        reset = 1;        
        #500 reset = 0;    
        #4000 reset = 1;  
        #1000 reset = 0;    
        #4000 $finish;    
    end

endmodule

Square_wave_assignment/square_wave.vcd
$date
	Thu May 15 19:22:51 2025
$end
$version
	Icarus Verilog
$end
$timescale
	1s
$end
$scope module tb_square_wave_gen $end
$var wire 1 ! out2 $end
$var wire 1 " out1 $end
$var reg 1 # clk $end
$var reg 1 $ reset $end
$scope module uut $end
$var wire 1 # clk $end
$var wire 1 $ reset $end
$var reg 2 % counter [1:0] $end
$var reg 1 " out1 $end
$var reg 1 ! out2 $end
$upscope $end
$upscope $end
$enddefinitions $end
$comment Show the parameter values. $end
$dumpall
$end
#0
$dumpvars
b0 %
1$
0#
0"
0!
$end
#125
1#
#250
0#
#375
1#
#500
1"
0#
0$
#625
1!
b1 %
1#
#750
0#
#875
0"
b10 %
1#
#1000
0#
#1125
0!
b11 %
1#
#1250
0#
#1375
1"
b0 %
1#
#1500
0#
#1625
1!
b1 %
1#
#1750
0#
#1875
0"
b10 %
1#
#2000
0#
#2125
0!
b11 %
1#
#2250
0#
#2375
1"
b0 %
1#
#2500
0#
#2625
1!
b1 %
1#
#2750
0#
#2875
0"
b10 %
1#
#3000
0#
#3125
0!
b11 %
1#
#3250
0#
#3375
1"
b0 %
1#
#3500
0#
#3625
1!
b1 %
1#
#3750
0#
#3875
0"
b10 %
1#
#4000
0#
#4125
0!
b11 %
1#
#4250
0#
#4375
1"
b0 %
1#
#4500
0"
0#
1$
#4625
1#
#4750
0#
#4875
1#
#5000
0#
#5125
1#
#5250
0#
#5375
1#
#5500
1"
0#
0$
#5625
1!
b1 %
1#
#5750
0#
#5875
0"
b10 %
1#
#6000
0#
#6125
0!
b11 %
1#
#6250
0#
#6375
1"
b0 %
1#
#6500
0#
#6625
1!
b1 %
1#
#6750
0#
#6875
0"
b10 %
1#
#7000
0#
#7125
0!
b11 %
1#
#7250
0#
#7375
1"
b0 %
1#
#7500
0#
#7625
1!
b1 %
1#
#7750
0#
#7875
0"
b10 %
1#
#8000
0#
#8125
0!
b11 %
1#
#8250
0#
#8375
1"
b0 %
1#
#8500
0#
#8625
1!
b1 %
1#
#8750
0#
#8875
0"
b10 %
1#
#9000
0#
#9125
0!
b11 %
1#
#9250
0#
#9375
1"
b0 %
1#
